llm_katan/__init__.py
llm_katan/cli.py
llm_katan/config.py
llm_katan/model.py
llm_katan/server.py
llm_katan-0.1.9.dist-info/METADATA
llm_katan-0.1.9.dist-info/WHEEL
llm_katan-0.1.9.dist-info/entry_points.txt
llm_katan-0.1.9.dist-info/top_level.txt
llm_katan-0.1.9.dist-info/RECORD
