Metadata-Version: 2.4
Name: llm-katan
Version: 0.1.9
Summary: LLM Katan - Lightweight LLM Server for Testing - Real tiny models with FastAPI and HuggingFace
Author-email: Yossi Ovadia <yovadia@redhat.com>
Maintainer-email: Yossi Ovadia <yovadia@redhat.com>
License: Apache-2.0
Project-URL: Homepage, https://github.com/vllm-project/semantic-router
Project-URL: Documentation, https://github.com/vllm-project/semantic-router/tree/main/e2e-tests/llm-katan
Project-URL: Repository, https://github.com/vllm-project/semantic-router.git
Project-URL: Issues, https://github.com/vllm-project/semantic-router/issues
Keywords: llm,testing,fastapi,huggingface,vllm,ai,ml
Classifier: Development Status :: 3 - Alpha
Classifier: Intended Audience :: Developers
Classifier: License :: OSI Approved :: Apache Software License
Classifier: Programming Language :: Python :: 3
Classifier: Programming Language :: Python :: 3.8
Classifier: Programming Language :: Python :: 3.9
Classifier: Programming Language :: Python :: 3.10
Classifier: Programming Language :: Python :: 3.11
Classifier: Programming Language :: Python :: 3.12
Classifier: Topic :: Software Development :: Testing
Classifier: Topic :: Scientific/Engineering :: Artificial Intelligence
Requires-Python: >=3.8
Requires-Dist: fastapi>=0.104.0
Requires-Dist: uvicorn[standard]>=0.24.0
Requires-Dist: transformers>=4.35.0
Requires-Dist: torch>=2.0.0
Requires-Dist: click>=8.0.0
Requires-Dist: pydantic>=2.0.0
Requires-Dist: numpy>=1.21.0
Provides-Extra: vllm
Requires-Dist: vllm>=0.2.0; extra == "vllm"
Provides-Extra: dev
Requires-Dist: pytest>=7.0.0; extra == "dev"
Requires-Dist: pytest-asyncio>=0.21.0; extra == "dev"
Requires-Dist: httpx>=0.24.0; extra == "dev"
Requires-Dist: black>=23.0.0; extra == "dev"
Requires-Dist: isort>=5.12.0; extra == "dev"
Requires-Dist: flake8>=6.0.0; extra == "dev"
